bpycv3d/CameraRandomizer.py
bpycv3d/DataCapture.py
bpycv3d/__init__.py
bpycv3d-1.1.0.dist-info/LICENSE.txt
bpycv3d-1.1.0.dist-info/METADATA
bpycv3d-1.1.0.dist-info/WHEEL
bpycv3d-1.1.0.dist-info/top_level.txt
bpycv3d-1.1.0.dist-info/RECORD
